{
  "conditions": [
    {
      "type":"is_loaded",
      "id":"futuremc"
    },
    {
      "type":"is_loaded",
      "id":"natura"
    }
  ],
  "type": "minecraft:crafting_shapeless",
  "ingredients": [
    [
      {
        "item": "natura:edibles",
        "data": 2
      },
      {
        "item": "natura:edibles",
        "data": 3
      },
      {
        "item": "natura:edibles",
        "data": 4
      },
      {
        "item": "natura:edibles",
        "data": 5
      }
    ],
    [
      {
        "item": "natura:edibles",
        "data": 2
      },
      {
        "item": "natura:edibles",
        "data": 3
      },
      {
        "item": "natura:edibles",
        "data": 4
      },
      {
        "item": "natura:edibles",
        "data": 5
      }
    ],
    {
      "item": "futuremc:honey_bottle"
    }
  ],
  "result":
    {
      "item": "vint:honey_berry",
      "count": 2
    }
}